mlora/__init__.py
mlora/dispatcher.py
mlora/evaluator.py
mlora/generator.py
mlora/model.py
mlora/prompter.py
mlora/tokenizer.py
mlora/trainer.py
mlora/utils.py
mlora/backends/__init__.py
mlora/backends/common.py
mlora/backends/cpu.py
mlora/backends/cuda.py
mlora/backends/mps.py
mlora/models/__init__.py
mlora/models/modeling_chatglm.py
mlora/models/modeling_gemma.py
mlora/models/modeling_gemma2.py
mlora/models/modeling_llama.py
mlora/models/modeling_mistral.py
mlora/models/modeling_phi.py
mlora/models/modeling_phi3.py
mlora/modules/__init__.py
mlora/modules/abstracts.py
mlora/modules/attention.py
mlora/modules/cache.py
mlora/modules/checkpoint.py
mlora/modules/config.py
mlora/modules/feed_forward.py
mlora/modules/lora_linear.py
mlora/modules/lora_moes.py
mlora/modules/mix_lora.py
mlora/modules/rope.py
mlora/tasks/__init__.py
mlora/tasks/common.py
mlora/tasks/glue_tasks.py
mlora/tasks/qa_tasks.py
mlora-0.5.2.dist-info/LICENSE
mlora-0.5.2.dist-info/METADATA
mlora-0.5.2.dist-info/WHEEL
mlora-0.5.2.dist-info/top_level.txt
mlora-0.5.2.dist-info/RECORD
