Metadata-Version: 2.1
Name: mlora
Version: 0.5.2
Summary: An Efficient Factory to Build Multiple LoRA Adapters
Project-URL: Homepage, https://github.com/mikecovlee/mLoRA
Project-URL: Bug Tracker, https://github.com/mikecovlee/mLoRA/issues
Classifier: Programming Language :: Python :: 3
Classifier: License :: OSI Approved :: Apache Software License
Classifier: Operating System :: OS Independent
Requires-Python: >=3.8
License-File: LICENSE
Requires-Dist: torch <2.4.0,>=2.3.0
Requires-Dist: datasets
Requires-Dist: evaluate
Requires-Dist: accelerate
Requires-Dist: transformers <4.45.0,>=4.44.0
Requires-Dist: sentencepiece
Requires-Dist: huggingface-hub
Requires-Dist: scikit-learn
Requires-Dist: tiktoken
